plotHicmain.py
command/__init__.py
command/plotHicpro.py
command/plotJuicerbox.py
command/runCommand.py
getMtxAxes/Hicproc.py
getMtxAxes/__init__.py
getMtxAxes/readHic.py
graph/Hicplot.py
graph/__init__.py
utils/MultiprocessMTX.py
utils/Pbarshow.py
utils/__init__.py
utils/commandUtils.py
plotHicGenome-0.1.1.dist-info/LICENSE
plotHicGenome-0.1.1.dist-info/METADATA
plotHicGenome-0.1.1.dist-info/WHEEL
plotHicGenome-0.1.1.dist-info/entry_points.txt
plotHicGenome-0.1.1.dist-info/top_level.txt
plotHicGenome-0.1.1.dist-info/RECORD
