Metadata-Version: 2.1
Name: plotHicGenome
Version: 0.1.1
Summary: THis package was used for showing Hicproc or juicerbox matrix
Home-page: http://example.com/HelloWorld/
Author: chenjhbio
Author-email: chenjunhui@genomics.cn
License: UNKNOWN
Project-URL: Documentation, https://docs.example.com/HelloWorld/
Project-URL: Source Code, https://code.example.com/HelloWorld/
Keywords: Hicproc,juicer
Platform: UNKNOWN
Classifier: Programming Language :: Python :: 3
Classifier: License :: OSI Approved :: Python Software Foundation License
Requires-Dist: matplotlib
Requires-Dist: numpy
Requires-Dist: scipy
Requires-Dist: pandas
